spec_cleaner/__init__.py
spec_cleaner/__main__.py
spec_cleaner/dependency_parser.py
spec_cleaner/fileutils.py
spec_cleaner/rpmbuild.py
spec_cleaner/rpmcheck.py
spec_cleaner/rpmcleaner.py
spec_cleaner/rpmcopyright.py
spec_cleaner/rpmdescription.py
spec_cleaner/rpmexception.py
spec_cleaner/rpmfiles.py
spec_cleaner/rpmhelpers.py
spec_cleaner/rpminstall.py
spec_cleaner/rpmpackage.py
spec_cleaner/rpmpreamble.py
spec_cleaner/rpmpreambleelements.py
spec_cleaner/rpmprep.py
spec_cleaner/rpmprune.py
spec_cleaner/rpmregexp.py
spec_cleaner/rpmrequirestoken.py
spec_cleaner/rpmscriplets.py
spec_cleaner/rpmsection.py
spec_cleaner-1.2.4.data/data/lib/obs/service/clean_spec_file
spec_cleaner-1.2.4.data/data/lib/obs/service/clean_spec_file.service
spec_cleaner-1.2.4.data/data/lib/obs/service/format_spec_file
spec_cleaner-1.2.4.data/data/lib/obs/service/format_spec_file.service
spec_cleaner-1.2.4.data/data/share/spec-cleaner/allowed_groups.txt
spec_cleaner-1.2.4.data/data/share/spec-cleaner/cmake_conversions.txt
spec_cleaner-1.2.4.data/data/share/spec-cleaner/excludes-bracketing.txt
spec_cleaner-1.2.4.data/data/share/spec-cleaner/licenses-suse.toml
spec_cleaner-1.2.4.data/data/share/spec-cleaner/licenses.toml
spec_cleaner-1.2.4.data/data/share/spec-cleaner/licenses_changes.txt
spec_cleaner-1.2.4.data/data/share/spec-cleaner/licenses_exceptions.txt
spec_cleaner-1.2.4.data/data/share/spec-cleaner/perl_conversions.txt
spec_cleaner-1.2.4.data/data/share/spec-cleaner/pkgconfig_conversions.txt
spec_cleaner-1.2.4.data/data/share/spec-cleaner/tex_conversions.txt
spec_cleaner-1.2.4.dist-info/licenses/AUTHORS
spec_cleaner-1.2.4.dist-info/licenses/COPYING
spec_cleaner-1.2.4.dist-info/METADATA
spec_cleaner-1.2.4.dist-info/WHEEL
spec_cleaner-1.2.4.dist-info/entry_points.txt
spec_cleaner-1.2.4.dist-info/top_level.txt
spec_cleaner-1.2.4.dist-info/RECORD
