Metadata-Version: 2.4
Name: spec_cleaner
Version: 1.2.4
Summary: RPM .spec files cleaner
Author-email: Daniel García Moreno <daniel.garcia@suse.com>, Kristyna Streitova <kstreitova@suse.com>, Tomáš Chvátal <tchvatal@suse.com>
License: BSD-3-Clause
Project-URL: Homepage, https://github.com/rpm-software-management/spec-cleaner
Project-URL: Repository, https://github.com/rpm-software-management/spec-cleaner.git
Project-URL: Issues, https://github.com/rpm-software-management/spec-cleaner/issues
Keywords: SUSE,RPM,.spec,cleaner
Platform: Linux
Classifier: Development Status :: 5 - Production/Stable
Classifier: Intended Audience :: Developers
Classifier: License :: OSI Approved :: BSD License
Classifier: Operating System :: Unix
Classifier: Operating System :: POSIX
Classifier: Programming Language :: Python
Classifier: Programming Language :: Python :: 3
Classifier: Topic :: Utilities
Classifier: Topic :: Text Processing
License-File: COPYING
License-File: AUTHORS
Requires-Dist: python-rpm-spec
Provides-Extra: tests
Requires-Dist: pytest; extra == "tests"
Requires-Dist: pytest-cov; extra == "tests"
Requires-Dist: pytest-xdist; extra == "tests"
Dynamic: license-file
